{
  "string": [
    {
      "name": "app_name",
      "value": "Sample App"
    },
    {
      "name": "entry_MainAbility",
      "value": "entry_MainAbility"
    },
    {
      "name": "mainability_description",
      "value": "Java_Empty Ability"
    },
    {
      "name": "mainability_HelloWorld",
      "value": "Hello World"
    },
    {
      "name": "testability_description",
      "value": "Java_Phone_Empty Feature Ability"
    },
    {
      "name": "testability_HelloWorld",
      "value": "Hello World"
    }
  ]
}